[{"family":"MaterialIcons","fonts":[{"asset":"fonts/MaterialIcons-Regular.otf"}]},{"family":"Konnect","fonts":[{"weight":100,"asset":"assets/fonts/KonnectThin.otf"},{"weight":100,"style":"italic","asset":"assets/fonts/KonnectThinItalic.otf"},{"weight":300,"asset":"assets/fonts/KonnectLight.otf"},{"weight":300,"style":"italic","asset":"assets/fonts/KonnectLightItalic.otf"},{"asset":"assets/fonts/KonnectRegular.otf"},{"style":"italic","asset":"assets/fonts/KonnectItalic.otf"},{"weight":500,"asset":"assets/fonts/KonnectMedium.otf"},{"weight":500,"style":"italic","asset":"assets/fonts/KonnectMediumItalic.otf"},{"weight":600,"asset":"assets/fonts/KonnectSemiBold.otf"},{"weight":600,"style":"italic","asset":"assets/fonts/KonnectSemiBoldItalic.otf"},{"weight":700,"asset":"assets/fonts/KonnectBold.otf"},{"weight":700,"style":"italic","asset":"assets/fonts/KonnectBoldItalic.otf"},{"weight":800,"asset":"assets/fonts/KonnectExtraBold.otf"},{"weight":800,"style":"italic","asset":"assets/fonts/KonnectExtraBoldItalic.otf"},{"weight":900,"style":"italic","asset":"assets/fonts/KonnectBlackItalic.otf"}]},{"family":"packages/cupertino_icons/CupertinoIcons","fonts":[{"asset":"packages/cupertino_icons/assets/CupertinoIcons.ttf"}]},{"family":"packages/font_awesome_flutter/FontAwesomeBrands","fonts":[{"weight":400,"asset":"packages/font_awesome_flutter/lib/fonts/fa-brands-400.ttf"}]},{"family":"packages/font_awesome_flutter/FontAwesomeRegular","fonts":[{"weight":400,"asset":"packages/font_awesome_flutter/lib/fonts/fa-regular-400.ttf"}]},{"family":"packages/font_awesome_flutter/FontAwesomeSolid","fonts":[{"weight":900,"asset":"packages/font_awesome_flutter/lib/fonts/fa-solid-900.ttf"}]}]